{
    "directed": true,
    "multigraph": false,
    "graph": {
        "node_default": {},
        "edge_default": {}
    },
    "nodes": [
        {
            "age": 8,
            "id": 1,
            "dominates": 5
        },
        {
            "age": 8,
            "id": 2,
            "dominates": 14
        },
        {
            "age": 4,
            "id": 3,
            "dominates": 18
        },
        {
            "age": 7,
            "id": 4,
            "dominates": 17
        },
        {
            "age": 8,
            "id": 5,
            "dominates": 2
        },
        {
            "age": 3,
            "id": 6,
            "dominates": 0
        },
        {
            "age": 5,
            "id": 7,
            "dominates": 16
        },
        {
            "age": 4,
            "id": 8,
            "dominates": 14
        },
        {
            "age": 7,
            "id": 9,
            "dominates": 16
        },
        {
            "age": 9,
            "id": 10,
            "dominates": 3
        },
        {
            "age": 6,
            "id": 11,
            "dominates": 10
        },
        {
            "age": 4,
            "id": 12,
            "dominates": 7
        },
        {
            "age": 9,
            "id": 13,
            "dominates": 14
        },
        {
            "age": 1,
            "id": 14,
            "dominates": 11
        },
        {
            "age": 9,
            "id": 15,
            "dominates": 11
        },
        {
            "age": 9,
            "id": 16,
            "dominates": 9
        },
        {
            "age": 4,
            "id": 17,
            "dominates": 7
        },
        {
            "age": 1,
            "id": 18,
            "dominates": 10
        },
        {
            "age": 1,
            "id": 19,
            "dominates": 7
        },
        {
            "age": 3,
            "id": 20,
            "dominates": 2
        },
        {
            "age": 3,
            "id": 21,
            "dominates": 1
        },
        {
            "age": 1,
            "id": 22,
            "dominates": 16
        },
        {
            "age": 7,
            "id": 23,
            "dominates": 9
        },
        {
            "age": 1,
            "id": 24,
            "dominates": 6
        },
        {
            "age": 9,
            "id": 25,
            "dominates": 6
        },
        {
            "age": 3,
            "id": 26,
            "dominates": 3
        },
        {
            "age": 4,
            "id": 27,
            "dominates": 1
        },
        {
            "age": 9,
            "id": 28,
            "dominates": 15
        }
    ],
    "links": [
        {
            "weight": 1,
            "source": "1",
            "target": "2"
        },
        {
            "weight": 1,
            "source": "1",
            "target": "3"
        },
        {
            "weight": 1,
            "source": "1",
            "target": "4"
        },
        {
            "weight": 1,
            "source": "1",
            "target": "5"
        },
        {
            "weight": 1,
            "source": "1",
            "target": "6"
        },
        {
            "weight": 1,
            "source": "2",
            "target": "4"
        },
        {
            "weight": 1,
            "source": "2",
            "target": "7"
        },
        {
            "weight": 5,
            "source": "2",
            "target": "8"
        },
        {
            "weight": 3,
            "source": "2",
            "target": "9"
        },
        {
            "weight": 1,
            "source": "2",
            "target": "12"
        },
        {
            "weight": 2,
            "source": "2",
            "target": "13"
        },
        {
            "weight": 1,
            "source": "2",
            "target": "15"
        },
        {
            "weight": 4,
            "source": "2",
            "target": "21"
        },
        {
            "weight": 1,
            "source": "2",
            "target": "22"
        },
        {
            "weight": 2,
            "source": "2",
            "target": "23"
        },
        {
            "weight": 3,
            "source": "2",
            "target": "24"
        },
        {
            "weight": 5,
            "source": "2",
            "target": "26"
        },
        {
            "weight": 2,
            "source": "2",
            "target": "27"
        },
        {
            "weight": 4,
            "source": "2",
            "target": "28"
        },
        {
            "weight": 1,
            "source": "3",
            "target": "2"
        },
        {
            "weight": 1,
            "source": "3",
            "target": "4"
        },
        {
            "weight": 1,
            "source": "3",
            "target": "5"
        },
        {
            "weight": 5,
            "source": "3",
            "target": "6"
        },
        {
            "weight": 1,
            "source": "3",
            "target": "8"
        },
        {
            "weight": 7,
            "source": "3",
            "target": "9"
        },
        {
            "weight": 7,
            "source": "3",
            "target": "14"
        },
        {
            "weight": 5,
            "source": "3",
            "target": "15"
        },
        {
            "weight": 2,
            "source": "3",
            "target": "16"
        },
        {
            "weight": 3,
            "source": "3",
            "target": "18"
        },
        {
            "weight": 5,
            "source": "3",
            "target": "19"
        },
        {
            "weight": 6,
            "source": "3",
            "target": "20"
        },
        {
            "weight": 1,
            "source": "3",
            "target": "21"
        },
        {
            "weight": 8,
            "source": "3",
            "target": "23"
        },
        {
            "weight": 2,
            "source": "3",
            "target": "24"
        },
        {
            "weight": 3,
            "source": "3",
            "target": "25"
        },
        {
            "weight": 4,
            "source": "3",
            "target": "26"
        },
        {
            "weight": 1,
            "source": "3",
            "target": "28"
        },
        {
            "weight": 1,
            "source": "4",
            "target": "2"
        },
        {
            "weight": 2,
            "source": "4",
            "target": "3"
        },
        {
            "weight": 1,
            "source": "4",
            "target": "5"
        },
        {
            "weight": 1,
            "source": "4",
            "target": "6"
        },
        {
            "weight": 1,
            "source": "4",
            "target": "11"
        },
        {
            "weight": 1,
            "source": "4",
            "target": "12"
        },
        {
            "weight": 2,
            "source": "4",
            "target": "15"
        },
        {
            "weight": 1,
            "source": "4",
            "target": "16"
        },
        {
            "weight": 2,
            "source": "4",
            "target": "18"
        },
        {
            "weight": 2,
            "source": "4",
            "target": "19"
        },
        {
            "weight": 1,
            "source": "4",
            "target": "20"
        },
        {
            "weight": 1,
            "source": "4",
            "target": "21"
        },
        {
            "weight": 1,
            "source": "4",
            "target": "23"
        },
        {
            "weight": 3,
            "source": "4",
            "target": "24"
        },
        {
            "weight": 2,
            "source": "4",
            "target": "25"
        },
        {
            "weight": 2,
            "source": "4",
            "target": "26"
        },
        {
            "weight": 1,
            "source": "4",
            "target": "27"
        },
        {
            "weight": 1,
            "source": "5",
            "target": "16"
        },
        {
            "weight": 1,
            "source": "5",
            "target": "21"
        },
        {
            "weight": 4,
            "source": "7",
            "target": "3"
        },
        {
            "weight": 2,
            "source": "7",
            "target": "4"
        },
        {
            "weight": 5,
            "source": "7",
            "target": "8"
        },
        {
            "weight": 2,
            "source": "7",
            "target": "9"
        },
        {
            "weight": 1,
            "source": "7",
            "target": "10"
        },
        {
            "weight": 1,
            "source": "7",
            "target": "11"
        },
        {
            "weight": 1,
            "source": "7",
            "target": "12"
        },
        {
            "weight": 4,
            "source": "7",
            "target": "13"
        },
        {
            "weight": 2,
            "source": "7",
            "target": "14"
        },
        {
            "weight": 3,
            "source": "7",
            "target": "15"
        },
        {
            "weight": 4,
            "source": "7",
            "target": "16"
        },
        {
            "weight": 1,
            "source": "7",
            "target": "17"
        },
        {
            "weight": 1,
            "source": "7",
            "target": "18"
        },
        {
            "weight": 7,
            "source": "7",
            "target": "19"
        },
        {
            "weight": 1,
            "source": "7",
            "target": "20"
        },
        {
            "weight": 4,
            "source": "7",
            "target": "21"
        },
        {
            "weight": 10,
            "source": "8",
            "target": "3"
        },
        {
            "weight": 3,
            "source": "8",
            "target": "4"
        },
        {
            "weight": 1,
            "source": "8",
            "target": "6"
        },
        {
            "weight": 1,
            "source": "8",
            "target": "9"
        },
        {
            "weight": 5,
            "source": "8",
            "target": "13"
        },
        {
            "weight": 4,
            "source": "8",
            "target": "15"
        },
        {
            "weight": 1,
            "source": "8",
            "target": "16"
        },
        {
            "weight": 1,
            "source": "8",
            "target": "17"
        },
        {
            "weight": 1,
            "source": "8",
            "target": "18"
        },
        {
            "weight": 8,
            "source": "8",
            "target": "19"
        },
        {
            "weight": 3,
            "source": "8",
            "target": "21"
        },
        {
            "weight": 7,
            "source": "8",
            "target": "23"
        },
        {
            "weight": 5,
            "source": "8",
            "target": "24"
        },
        {
            "weight": 6,
            "source": "8",
            "target": "26"
        },
        {
            "weight": 3,
            "source": "9",
            "target": "4"
        },
        {
            "weight": 4,
            "source": "9",
            "target": "6"
        },
        {
            "weight": 2,
            "source": "9",
            "target": "11"
        },
        {
            "weight": 2,
            "source": "9",
            "target": "13"
        },
        {
            "weight": 4,
            "source": "9",
            "target": "14"
        },
        {
            "weight": 1,
            "source": "9",
            "target": "15"
        },
        {
            "weight": 2,
            "source": "9",
            "target": "16"
        },
        {
            "weight": 2,
            "source": "9",
            "target": "17"
        },
        {
            "weight": 3,
            "source": "9",
            "target": "18"
        },
        {
            "weight": 4,
            "source": "9",
            "target": "19"
        },
        {
            "weight": 2,
            "source": "9",
            "target": "20"
        },
        {
            "weight": 1,
            "source": "9",
            "target": "21"
        },
        {
            "weight": 3,
            "source": "9",
            "target": "23"
        },
        {
            "weight": 3,
            "source": "9",
            "target": "25"
        },
        {
            "weight": 9,
            "source": "9",
            "target": "26"
        },
        {
            "weight": 7,
            "source": "9",
            "target": "28"
        },
        {
            "weight": 1,
            "source": "10",
            "target": "16"
        },
        {
            "weight": 1,
            "source": "10",
            "target": "27"
        },
        {
            "weight": 1,
            "source": "10",
            "target": "22"
        },
        {
            "weight": 1,
            "source": "11",
            "target": "3"
        },
        {
            "weight": 1,
            "source": "11",
            "target": "5"
        },
        {
            "weight": 2,
            "source": "11",
            "target": "14"
        },
        {
            "weight": 1,
            "source": "11",
            "target": "16"
        },
        {
            "weight": 2,
            "source": "11",
            "target": "17"
        },
        {
            "weight": 1,
            "source": "11",
            "target": "18"
        },
        {
            "weight": 1,
            "source": "11",
            "target": "21"
        },
        {
            "weight": 2,
            "source": "11",
            "target": "23"
        },
        {
            "weight": 1,
            "source": "11",
            "target": "25"
        },
        {
            "weight": 2,
            "source": "11",
            "target": "26"
        },
        {
            "weight": 2,
            "source": "12",
            "target": "2"
        },
        {
            "weight": 1,
            "source": "12",
            "target": "5"
        },
        {
            "weight": 1,
            "source": "12",
            "target": "9"
        },
        {
            "weight": 5,
            "source": "12",
            "target": "16"
        },
        {
            "weight": 2,
            "source": "12",
            "target": "20"
        },
        {
            "weight": 1,
            "source": "12",
            "target": "21"
        },
        {
            "weight": 1,
            "source": "12",
            "target": "26"
        },
        {
            "weight": 5,
            "source": "13",
            "target": "3"
        },
        {
            "weight": 3,
            "source": "13",
            "target": "6"
        },
        {
            "weight": 2,
            "source": "13",
            "target": "11"
        },
        {
            "weight": 2,
            "source": "13",
            "target": "14"
        },
        {
            "weight": 2,
            "source": "13",
            "target": "15"
        },
        {
            "weight": 1,
            "source": "13",
            "target": "17"
        },
        {
            "weight": 1,
            "source": "13",
            "target": "18"
        },
        {
            "weight": 3,
            "source": "13",
            "target": "19"
        },
        {
            "weight": 2,
            "source": "13",
            "target": "20"
        },
        {
            "weight": 2,
            "source": "13",
            "target": "23"
        },
        {
            "weight": 3,
            "source": "13",
            "target": "24"
        },
        {
            "weight": 2,
            "source": "13",
            "target": "25"
        },
        {
            "weight": 1,
            "source": "13",
            "target": "26"
        },
        {
            "weight": 1,
            "source": "13",
            "target": "27"
        },
        {
            "weight": 2,
            "source": "14",
            "target": "4"
        },
        {
            "weight": 1,
            "source": "14",
            "target": "6"
        },
        {
            "weight": 1,
            "source": "14",
            "target": "11"
        },
        {
            "weight": 3,
            "source": "14",
            "target": "13"
        },
        {
            "weight": 7,
            "source": "14",
            "target": "17"
        },
        {
            "weight": 4,
            "source": "14",
            "target": "19"
        },
        {
            "weight": 3,
            "source": "14",
            "target": "20"
        },
        {
            "weight": 1,
            "source": "14",
            "target": "21"
        },
        {
            "weight": 3,
            "source": "14",
            "target": "24"
        },
        {
            "weight": 3,
            "source": "14",
            "target": "25"
        },
        {
            "weight": 3,
            "source": "14",
            "target": "26"
        },
        {
            "weight": 1,
            "source": "15",
            "target": "6"
        },
        {
            "weight": 2,
            "source": "15",
            "target": "14"
        },
        {
            "weight": 1,
            "source": "15",
            "target": "17"
        },
        {
            "weight": 2,
            "source": "15",
            "target": "18"
        },
        {
            "weight": 3,
            "source": "15",
            "target": "19"
        },
        {
            "weight": 2,
            "source": "15",
            "target": "20"
        },
        {
            "weight": 2,
            "source": "15",
            "target": "21"
        },
        {
            "weight": 6,
            "source": "15",
            "target": "23"
        },
        {
            "weight": 1,
            "source": "15",
            "target": "24"
        },
        {
            "weight": 3,
            "source": "15",
            "target": "26"
        },
        {
            "weight": 1,
            "source": "15",
            "target": "27"
        },
        {
            "weight": 4,
            "source": "16",
            "target": "2"
        },
        {
            "weight": 1,
            "source": "16",
            "target": "6"
        },
        {
            "weight": 2,
            "source": "16",
            "target": "15"
        },
        {
            "weight": 1,
            "source": "16",
            "target": "17"
        },
        {
            "weight": 2,
            "source": "16",
            "target": "18"
        },
        {
            "weight": 2,
            "source": "16",
            "target": "19"
        },
        {
            "weight": 2,
            "source": "16",
            "target": "20"
        },
        {
            "weight": 1,
            "source": "16",
            "target": "21"
        },
        {
            "weight": 1,
            "source": "16",
            "target": "26"
        },
        {
            "weight": 1,
            "source": "17",
            "target": "6"
        },
        {
            "weight": 1,
            "source": "17",
            "target": "13"
        },
        {
            "weight": 1,
            "source": "17",
            "target": "14"
        },
        {
            "weight": 1,
            "source": "17",
            "target": "20"
        },
        {
            "weight": 1,
            "source": "17",
            "target": "21"
        },
        {
            "weight": 1,
            "source": "17",
            "target": "25"
        },
        {
            "weight": 2,
            "source": "17",
            "target": "27"
        },
        {
            "weight": 1,
            "source": "18",
            "target": "4"
        },
        {
            "weight": 6,
            "source": "18",
            "target": "6"
        },
        {
            "weight": 3,
            "source": "18",
            "target": "19"
        },
        {
            "weight": 2,
            "source": "18",
            "target": "20"
        },
        {
            "weight": 4,
            "source": "18",
            "target": "21"
        },
        {
            "weight": 10,
            "source": "18",
            "target": "23"
        },
        {
            "weight": 1,
            "source": "18",
            "target": "24"
        },
        {
            "weight": 1,
            "source": "18",
            "target": "25"
        },
        {
            "weight": 4,
            "source": "18",
            "target": "26"
        },
        {
            "weight": 3,
            "source": "18",
            "target": "27"
        },
        {
            "weight": 5,
            "source": "19",
            "target": "6"
        },
        {
            "weight": 1,
            "source": "19",
            "target": "18"
        },
        {
            "weight": 1,
            "source": "19",
            "target": "20"
        },
        {
            "weight": 5,
            "source": "19",
            "target": "24"
        },
        {
            "weight": 1,
            "source": "19",
            "target": "25"
        },
        {
            "weight": 2,
            "source": "19",
            "target": "26"
        },
        {
            "weight": 1,
            "source": "19",
            "target": "27"
        },
        {
            "weight": 1,
            "source": "20",
            "target": "26"
        },
        {
            "weight": 3,
            "source": "20",
            "target": "21"
        },
        {
            "weight": 10,
            "source": "21",
            "target": "6"
        },
        {
            "weight": 12,
            "source": "22",
            "target": "3"
        },
        {
            "weight": 1,
            "source": "22",
            "target": "4"
        },
        {
            "weight": 3,
            "source": "22",
            "target": "6"
        },
        {
            "weight": 7,
            "source": "22",
            "target": "8"
        },
        {
            "weight": 4,
            "source": "22",
            "target": "9"
        },
        {
            "weight": 2,
            "source": "22",
            "target": "13"
        },
        {
            "weight": 2,
            "source": "22",
            "target": "14"
        },
        {
            "weight": 2,
            "source": "22",
            "target": "15"
        },
        {
            "weight": 2,
            "source": "22",
            "target": "18"
        },
        {
            "weight": 6,
            "source": "22",
            "target": "19"
        },
        {
            "weight": 4,
            "source": "22",
            "target": "21"
        },
        {
            "weight": 12,
            "source": "22",
            "target": "23"
        },
        {
            "weight": 4,
            "source": "22",
            "target": "24"
        },
        {
            "weight": 2,
            "source": "22",
            "target": "25"
        },
        {
            "weight": 1,
            "source": "22",
            "target": "26"
        },
        {
            "weight": 1,
            "source": "22",
            "target": "27"
        },
        {
            "weight": 2,
            "source": "23",
            "target": "6"
        },
        {
            "weight": 1,
            "source": "23",
            "target": "14"
        },
        {
            "weight": 1,
            "source": "23",
            "target": "17"
        },
        {
            "weight": 1,
            "source": "23",
            "target": "19"
        },
        {
            "weight": 3,
            "source": "23",
            "target": "20"
        },
        {
            "weight": 4,
            "source": "23",
            "target": "21"
        },
        {
            "weight": 1,
            "source": "23",
            "target": "25"
        },
        {
            "weight": 2,
            "source": "23",
            "target": "26"
        },
        {
            "weight": 2,
            "source": "23",
            "target": "27"
        },
        {
            "weight": 11,
            "source": "24",
            "target": "6"
        },
        {
            "weight": 3,
            "source": "24",
            "target": "18"
        },
        {
            "weight": 3,
            "source": "24",
            "target": "20"
        },
        {
            "weight": 4,
            "source": "24",
            "target": "21"
        },
        {
            "weight": 1,
            "source": "24",
            "target": "23"
        },
        {
            "weight": 3,
            "source": "24",
            "target": "26"
        },
        {
            "weight": 2,
            "source": "25",
            "target": "6"
        },
        {
            "weight": 2,
            "source": "25",
            "target": "14"
        },
        {
            "weight": 3,
            "source": "25",
            "target": "18"
        },
        {
            "weight": 8,
            "source": "25",
            "target": "20"
        },
        {
            "weight": 2,
            "source": "25",
            "target": "21"
        },
        {
            "weight": 8,
            "source": "25",
            "target": "24"
        },
        {
            "weight": 5,
            "source": "26",
            "target": "20"
        },
        {
            "weight": 1,
            "source": "26",
            "target": "21"
        },
        {
            "weight": 2,
            "source": "26",
            "target": "6"
        },
        {
            "weight": 1,
            "source": "27",
            "target": "26"
        },
        {
            "weight": 1,
            "source": "28",
            "target": "3"
        },
        {
            "weight": 2,
            "source": "28",
            "target": "6"
        },
        {
            "weight": 1,
            "source": "28",
            "target": "11"
        },
        {
            "weight": 1,
            "source": "28",
            "target": "12"
        },
        {
            "weight": 3,
            "source": "28",
            "target": "14"
        },
        {
            "weight": 1,
            "source": "28",
            "target": "16"
        },
        {
            "weight": 1,
            "source": "28",
            "target": "17"
        },
        {
            "weight": 2,
            "source": "28",
            "target": "19"
        },
        {
            "weight": 1,
            "source": "28",
            "target": "20"
        },
        {
            "weight": 3,
            "source": "28",
            "target": "21"
        },
        {
            "weight": 8,
            "source": "28",
            "target": "22"
        },
        {
            "weight": 2,
            "source": "28",
            "target": "23"
        },
        {
            "weight": 2,
            "source": "28",
            "target": "25"
        },
        {
            "weight": 3,
            "source": "28",
            "target": "26"
        },
        {
            "weight": 1,
            "source": "28",
            "target": "27"
        }
    ]
}